whippet/__init__.py
whippet/console.py
whippet/hook_template
whippet/whippet.py
whippet-0.3.2.dist-info/entry_points.txt
whippet-0.3.2.dist-info/LICENSE.txt
whippet-0.3.2.dist-info/WHEEL
whippet-0.3.2.dist-info/METADATA
whippet-0.3.2.dist-info/RECORD
