Metadata-Version: 2.1
Name: whippet
Version: 0.3.2
Summary: Install make based git hooks with ease.
Home-page: https://github.com/BorePlusPlus/whippet
License: MIT
Author: Dalibor Novak
Author-email: BorePlusPlus@gmail.com
Requires-Python: >=3.6,<4.0
Classifier: License :: OSI Approved :: MIT License
Classifier: Programming Language :: Python :: 3
Classifier: Programming Language :: Python :: 3.6
Classifier: Programming Language :: Python :: 3.7
